odoo/addons/pos_lot_selection/README.rst
odoo/addons/pos_lot_selection/__init__.py
odoo/addons/pos_lot_selection/__manifest__.py
odoo/addons/pos_lot_selection/i18n/es.po
odoo/addons/pos_lot_selection/models/__init__.py
odoo/addons/pos_lot_selection/models/pos_session.py
odoo/addons/pos_lot_selection/static/description/icon.png
odoo/addons/pos_lot_selection/static/src/js/orderline.js
odoo/addons/pos_lot_selection/static/src/js/popup/LotSelectorPopup.js
odoo/addons/pos_lot_selection/static/src/js/popup/ProductScreen.js
odoo/addons/pos_lot_selection/static/src/js/popup/StockProductionLot.js
odoo/addons/pos_lot_selection/static/src/xml/LotSelectorPopup.xml
odoo/addons/pos_lot_selection/views/assets.xml
odoo14_addon_pos_lot_selection-14.0.2.0.0.dist-info/METADATA
odoo14_addon_pos_lot_selection-14.0.2.0.0.dist-info/WHEEL
odoo14_addon_pos_lot_selection-14.0.2.0.0.dist-info/top_level.txt
odoo14_addon_pos_lot_selection-14.0.2.0.0.dist-info/RECORD
